[{"mix_id":2105426208262,"mix_sid":"qv7wejgm","id":8449,"name":"RY5","vendor":{"name":"Super Concentrates","abbreviation":"SC","mix_id":2111225411247,"mix_sid":"qxvt3l4f"},"created_at":"2017-07-16T21:43:55.000-04:00","updated_at":"2017-07-16T22:15:10.000-04:00","deleted":null,"deleted_at":null,"recipe_count":0,"average_millipercent":0,"slug":"super-concentrates-ry5","confirmed":true,"rejected":false,"vendor_url":"http://www.diy-ejuice.com/RY5-Concentrated-Flavor-p/conc-ry5.htm","base":null,"density":1.0,"imageUrl":"","description":null,"description_raw":null,"short_description":null,"vendor_percentage":0.0,"vendor_description_raw":null,"vendor_description":null,"other_names":"","discontinued":false,"tags":{}},{"mix_id":2134740794935,"mix_sid":"r8opjvav","id":8450,"name":"Tobacco","vendor":{"name":"Super Concentrates","abbreviation":"SC","mix_id":2111225411247,"mix_sid":"qxvt3l4f"},"created_at":"2017-07-16T21:43:55.000-04:00","updated_at":"2017-07-16T22:15:10.000-04:00","deleted":null,"deleted_at":null,"recipe_count":0,"average_millipercent":0,"slug":"super-concentrates-tobacco","confirmed":true,"rejected":false,"vendor_url":"http://www.diy-ejuice.com/Tobacco-Super-Concentrated-Flavor-p/conc-tobacco.htm","base":null,"density":1.0,"imageUrl":"","description":null,"description_raw":null,"short_description":null,"vendor_percentage":0.0,"vendor_description_raw":null,"vendor_description":null,"other_names":"","discontinued":false,"tags":{}},{"mix_id":2111691797500,"mix_sid":"qy3irv24","id":8451,"name":"Virginia Tobacco","vendor":{"name":"Super Concentrates","abbreviation":"SC","mix_id":2111225411247,"mix_sid":"qxvt3l4f"},"created_at":"2017-07-16T21:43:55.000-04:00","updated_at":"2017-07-16T22:15:11.000-04:00","deleted":null,"deleted_at":null,"recipe_count":0,"average_millipercent":0,"slug":"super-concentrates-virginia-tobacco","confirmed":true,"rejected":false,"vendor_url":"http://www.diy-ejuice.com/Virginia-Tobacco-Super-Concentrated-Flavor-p/conc-virginia.htm","base":null,"density":1.0,"imageUrl":"","description":null,"description_raw":null,"short_description":null,"vendor_percentage":0.0,"vendor_description_raw":null,"vendor_description":null,"other_names":"","discontinued":false,"tags":{}},{"mix_id":2159335850869,"mix_sid":"rjzgt9x1","id":8456,"name":"Fuji Apple","vendor":{"name":"Capella","abbreviation":"CAP","mix_id":2104525803850,"mix_sid":"qut0bqyy"},"created_at":"2017-07-17T22:09:48.000-04:00","updated_at":"2019-06-22T18:36:09.000-04:00","deleted":null,"deleted_at":null,"recipe_count":380,"average_millipercent":2891,"slug":"capella-fuji-apple","confirmed":true,"rejected":false,"vendor_url":"http://www.capellaflavors.com/products/fuji-apple-flavor-concentrate-13ml.html","base":null,"density":1.0,"imageUrl":"","description":null,"description_raw":null,"short_description":null,"vendor_percentage":0.0,"vendor_description_raw":null,"vendor_description":null,"other_names":"","discontinued":false,"tags":{}},{"mix_id":2063463707694,"mix_sid":"qbxx0isu","id":8464,"name":"Almond Toffee Candy","vendor":{"name":"Flavor West","abbreviation":"FW","mix_id":2163807369996,"mix_sid":"rm1f1g5o"},"created_at":"2017-07-20T18:55:09.000-04:00","updated_at":"2017-07-20T19:25:01.000-04:00","deleted":null,"deleted_at":null,"recipe_count":0,"average_millipercent":0,"slug":"flavor-west-almond-toffee-candy","confirmed":true,"rejected":false,"vendor_url":"http://flavorwest.com/index.php/water-soluble-flavoring/almond-toffee-candy.html","base":null,"density":1.0,"imageUrl":"","description":null,"description_raw":null,"short_description":null,"vendor_percentage":0.0,"vendor_description_raw":null,"vendor_description":null,"other_names":"","discontinued":false,"tags":{}},{"mix_id":2100986986909,"mix_sid":"qt6hemcd","id":8465,"name":"Apple (Red,Natural)","vendor":{"name":"Flavor West","abbreviation":"FW","mix_id":2163807369996,"mix_sid":"rm1f1g5o"},"created_at":"2017-07-20T18:55:09.000-04:00","updated_at":"2017-07-20T19:25:01.000-04:00","deleted":null,"deleted_at":null,"recipe_count":0,"average_millipercent":0,"slug":"flavor-west-apple-red-natural","confirmed":true,"rejected":false,"vendor_url":"http://flavorwest.com/index.php/water-soluble-flavoring/apple-red-natural.html","base":null,"density":1.0,"imageUrl":"","description":null,"description_raw":null,"short_description":null,"vendor_percentage":0.0,"vendor_description_raw":null,"vendor_description":null,"other_names":"","discontinued":false,"tags":{}},{"mix_id":2057243989084,"mix_sid":"q931yd7g","id":8466,"name":"Apple (Green,Natural)","vendor":{"name":"Flavor West","abbreviation":"FW","mix_id":2163807369996,"mix_sid":"rm1f1g5o"},"created_at":"2017-07-20T18:55:10.000-04:00","updated_at":"2018-08-14T21:36:39.000-04:00","deleted":null,"deleted_at":null,"recipe_count":0,"average_millipercent":0,"slug":"flavor-west-apple-green-natural","confirmed":true,"rejected":false,"vendor_url":"http://flavorwest.com/index.php/water-soluble-flavoring/apple-green-natural.html","base":null,"density":1.0,"imageUrl":"","description":null,"description_raw":null,"short_description":null,"vendor_percentage":0.0,"vendor_description_raw":null,"vendor_description":null,"other_names":"","discontinued":false,"tags":{}},{"mix_id":2047983074782,"mix_sid":"q4tw8tzy","id":8467,"name":"Big Stick","vendor":{"name":"Flavor West","abbreviation":"FW","mix_id":2163807369996,"mix_sid":"rm1f1g5o"},"created_at":"2017-07-20T18:55:10.000-04:00","updated_at":"2018-07-25T04:35:40.000-04:00","deleted":null,"deleted_at":null,"recipe_count":3,"average_millipercent":3000,"slug":"flavor-west-big-stick","confirmed":true,"rejected":false,"vendor_url":"http://flavorwest.com/index.php/water-soluble-flavoring/big-stick.html","base":null,"density":1.0,"imageUrl":"","description":null,"description_raw":null,"short_description":null,"vendor_percentage":0.0,"vendor_description_raw":null,"vendor_description":null,"other_names":"","discontinued":false,"tags":{}},{"mix_id":2124745796961,"mix_sid":"r43esdi9","id":8468,"name":"Birthday Cake","vendor":{"name":"Flavor West","abbreviation":"FW","mix_id":2163807369996,"mix_sid":"rm1f1g5o"},"created_at":"2017-07-20T18:55:11.000-04:00","updated_at":"2019-06-16T12:24:01.000-04:00","deleted":null,"deleted_at":null,"recipe_count":54,"average_millipercent":2547,"slug":"flavor-west-birthday-cake","confirmed":true,"rejected":false,"vendor_url":"http://flavorwest.com/index.php/water-soluble-flavoring/birthday-cake.html","base":null,"density":1.0,"imageUrl":"","description":null,"description_raw":null,"short_description":null,"vendor_percentage":0.0,"vendor_description_raw":null,"vendor_description":null,"other_names":"","discontinued":false,"tags":{}},{"mix_id":2080043793132,"mix_sid":"qjk4dalo","id":8469,"name":"Butterbeer","vendor":{"name":"Flavor West","abbreviation":"FW","mix_id":2163807369996,"mix_sid":"rm1f1g5o"},"created_at":"2017-07-20T18:55:12.000-04:00","updated_at":"2019-03-15T14:41:28.000-04:00","deleted":null,"deleted_at":null,"recipe_count":9,"average_millipercent":4084,"slug":"flavor-west-butterbeer","confirmed":true,"rejected":false,"vendor_url":"http://flavorwest.com/index.php/water-soluble-flavoring/butterbeer.html","base":null,"density":1.0,"imageUrl":"","description":null,"description_raw":null,"short_description":null,"vendor_percentage":0.0,"vendor_description_raw":null,"vendor_description":null,"other_names":"","discontinued":false,"tags":{}},{"mix_id":2138167560063,"mix_sid":"ra9drc73","id":8470,"name":"Cake (White)","vendor":{"name":"Flavor West","abbreviation":"FW","mix_id":2163807369996,"mix_sid":"rm1f1g5o"},"created_at":"2017-07-20T18:55:13.000-04:00","updated_at":"2019-06-17T16:45:27.000-04:00","deleted":null,"deleted_at":null,"recipe_count":122,"average_millipercent":2715,"slug":"flavor-west-cake-white","confirmed":true,"rejected":false,"vendor_url":"http://flavorwest.com/index.php/water-soluble-flavoring/cake-white.html","base":null,"density":1.0,"imageUrl":"","description":null,"description_raw":null,"short_description":null,"vendor_percentage":0.0,"vendor_description_raw":null,"vendor_description":null,"other_names":"","discontinued":false,"tags":{}},{"mix_id":2166594622203,"mix_sid":"rnbihxq3","id":8471,"name":"Candy Bar","vendor":{"name":"Flavor West","abbreviation":"FW","mix_id":2163807369996,"mix_sid":"rm1f1g5o"},"created_at":"2017-07-20T18:55:13.000-04:00","updated_at":"2017-07-20T19:25:04.000-04:00","deleted":null,"deleted_at":null,"recipe_count":0,"average_millipercent":0,"slug":"flavor-west-candy-bar","confirmed":true,"rejected":false,"vendor_url":"http://flavorwest.com/index.php/water-soluble-flavoring/candy-bar.html","base":null,"density":1.0,"imageUrl":"","description":null,"description_raw":null,"short_description":null,"vendor_percentage":0.0,"vendor_description_raw":null,"vendor_description":null,"other_names":"","discontinued":false,"tags":{}},{"mix_id":2112776401886,"mix_sid":"qylgip5q","id":8472,"name":"Chocolate Wafer Bar","vendor":{"name":"Flavor West","abbreviation":"FW","mix_id":2163807369996,"mix_sid":"rm1f1g5o"},"created_at":"2017-07-20T18:55:15.000-04:00","updated_at":"2019-04-18T23:40:50.000-04:00","deleted":null,"deleted_at":null,"recipe_count":2,"average_millipercent":1000,"slug":"flavor-west-chocolate-wafer-bar","confirmed":true,"rejected":false,"vendor_url":"http://flavorwest.com/index.php/water-soluble-flavoring/chocolate-wafer-bar.html","base":null,"density":1.0,"imageUrl":"","description":null,"description_raw":null,"short_description":null,"vendor_percentage":0.0,"vendor_description_raw":null,"vendor_description":null,"other_names":"","discontinued":false,"tags":{}},{"mix_id":2068794166930,"mix_sid":"qee2mrgy","id":8473,"name":"Circus Peanuts","vendor":{"name":"Flavor West","abbreviation":"FW","mix_id":2163807369996,"mix_sid":"rm1f1g5o"},"created_at":"2017-07-20T18:55:15.000-04:00","updated_at":"2017-07-20T19:25:05.000-04:00","deleted":null,"deleted_at":null,"recipe_count":0,"average_millipercent":0,"slug":"flavor-west-circus-peanuts","confirmed":true,"rejected":false,"vendor_url":"http://flavorwest.com/index.php/water-soluble-flavoring/circus-peanuts.html","base":null,"density":1.0,"imageUrl":"","description":null,"description_raw":null,"short_description":null,"vendor_percentage":0.0,"vendor_description_raw":null,"vendor_description":null,"other_names":"","discontinued":false,"tags":{}},{"mix_id":2045459676222,"mix_sid":"q3o5vn7i","id":8474,"name":"Citrus Punch","vendor":{"name":"Flavor West","abbreviation":"FW","mix_id":2163807369996,"mix_sid":"rm1f1g5o"},"created_at":"2017-07-20T18:55:16.000-04:00","updated_at":"2017-11-10T03:14:28.000-05:00","deleted":null,"deleted_at":null,"recipe_count":1,"average_millipercent":1500,"slug":"flavor-west-citrus-punch","confirmed":true,"rejected":false,"vendor_url":"http://flavorwest.com/index.php/water-soluble-flavoring/citrus-punch.html","base":null,"density":1.0,"imageUrl":"","description":null,"description_raw":null,"short_description":null,"vendor_percentage":0.0,"vendor_description_raw":null,"vendor_description":null,"other_names":"","discontinued":false,"tags":{}},{"mix_id":2121437219489,"mix_sid":"r2koy2sh","id":8475,"name":"Citrus Soda","vendor":{"name":"Flavor West","abbreviation":"FW","mix_id":2163807369996,"mix_sid":"rm1f1g5o"},"created_at":"2017-07-20T18:55:16.000-04:00","updated_at":"2019-06-19T18:31:21.000-04:00","deleted":null,"deleted_at":null,"recipe_count":3,"average_millipercent":2584,"slug":"flavor-west-citrus-soda","confirmed":true,"rejected":false,"vendor_url":"http://flavorwest.com/index.php/water-soluble-flavoring/citrus-soda.html","base":null,"density":1.0,"imageUrl":"","description":null,"description_raw":null,"short_description":null,"vendor_percentage":0.0,"vendor_description_raw":null,"vendor_description":null,"other_names":"","discontinued":false,"tags":{}},{"mix_id":2128474731485,"mix_sid":"r5t2wdst","id":8476,"name":"Coffee Cake","vendor":{"name":"Flavor West","abbreviation":"FW","mix_id":2163807369996,"mix_sid":"rm1f1g5o"},"created_at":"2017-07-20T18:55:17.000-04:00","updated_at":"2019-01-12T23:28:58.000-05:00","deleted":null,"deleted_at":null,"recipe_count":3,"average_millipercent":4000,"slug":"flavor-west-coffee-cake","confirmed":true,"rejected":false,"vendor_url":"http://flavorwest.com/index.php/water-soluble-flavoring/coffee-cake.html","base":null,"density":1.0,"imageUrl":"","description":null,"description_raw":null,"short_description":null,"vendor_percentage":0.0,"vendor_description_raw":null,"vendor_description":null,"other_names":"","discontinued":false,"tags":{}},{"mix_id":2121050051058,"mix_sid":"r2eafppu","id":8477,"name":"Creamy Chocolate Cake","vendor":{"name":"Flavor West","abbreviation":"FW","mix_id":2163807369996,"mix_sid":"rm1f1g5o"},"created_at":"2017-07-20T18:55:17.000-04:00","updated_at":"2019-01-13T17:32:11.000-05:00","deleted":null,"deleted_at":null,"recipe_count":2,"average_millipercent":5000,"slug":"flavor-west-creamy-chocolate-cake","confirmed":true,"rejected":false,"vendor_url":"http://flavorwest.com/index.php/water-soluble-flavoring/dong-ding.html","base":null,"density":1.0,"imageUrl":"","description":null,"description_raw":null,"short_description":null,"vendor_percentage":0.0,"vendor_description_raw":null,"vendor_description":null,"other_names":"","discontinued":false,"tags":{}},{"mix_id":2123015874397,"mix_sid":"r3asu4pp","id":8478,"name":"Creamy Sponge Cake","vendor":{"name":"Flavor West","abbreviation":"FW","mix_id":2163807369996,"mix_sid":"rm1f1g5o"},"created_at":"2017-07-20T18:55:18.000-04:00","updated_at":"2019-06-17T16:45:27.000-04:00","deleted":null,"deleted_at":null,"recipe_count":50,"average_millipercent":2715,"slug":"flavor-west-creamy-sponge-cake","confirmed":true,"rejected":false,"vendor_url":"http://flavorwest.com/index.php/water-soluble-flavoring/creamy-sponge-cake.html","base":null,"density":1.0,"imageUrl":"","description":null,"description_raw":null,"short_description":null,"vendor_percentage":0.0,"vendor_description_raw":null,"vendor_description":null,"other_names":"","discontinued":false,"tags":{}},{"mix_id":2143532660030,"mix_sid":"rcq401tq","id":8479,"name":"Crunch Fruit Cereal","vendor":{"name":"Flavor West","abbreviation":"FW","mix_id":2163807369996,"mix_sid":"rm1f1g5o"},"created_at":"2017-07-20T18:55:18.000-04:00","updated_at":"2019-06-19T15:32:56.000-04:00","deleted":null,"deleted_at":null,"recipe_count":13,"average_millipercent":3039,"slug":"flavor-west-crunch-fruit-cereal","confirmed":true,"rejected":false,"vendor_url":"http://flavorwest.com/index.php/water-soluble-flavoring/crunch-fruit-cereal.html","base":null,"density":1.0,"imageUrl":"","description":null,"description_raw":null,"short_description":null,"vendor_percentage":0.0,"vendor_description_raw":null,"vendor_description":null,"other_names":"","discontinued":false,"tags":{}},{"mix_id":2050923042777,"mix_sid":"q66imjtl","id":8480,"name":"Funnel Cake","vendor":{"name":"Flavor West","abbreviation":"FW","mix_id":2163807369996,"mix_sid":"rm1f1g5o"},"created_at":"2017-07-20T18:55:19.000-04:00","updated_at":"2017-08-29T19:15:25.000-04:00","deleted":null,"deleted_at":null,"recipe_count":2,"average_millipercent":3000,"slug":"flavor-west-funnel-cake","confirmed":true,"rejected":false,"vendor_url":"http://flavorwest.com/index.php/water-soluble-flavoring/funnel-cake.html","base":null,"density":1.0,"imageUrl":"","description":null,"description_raw":null,"short_description":null,"vendor_percentage":0.0,"vendor_description_raw":null,"vendor_description":null,"other_names":"","discontinued":false,"tags":{}},{"mix_id":2163039028311,"mix_sid":"rlopl7x3","id":8481,"name":"Glazed Doughnut","vendor":{"name":"Flavor West","abbreviation":"FW","mix_id":2163807369996,"mix_sid":"rm1f1g5o"},"created_at":"2017-07-20T18:55:20.000-04:00","updated_at":"2019-03-15T21:53:04.000-04:00","deleted":null,"deleted_at":null,"recipe_count":7,"average_millipercent":3286,"slug":"flavor-west-glazed-doughnut","confirmed":true,"rejected":false,"vendor_url":"http://flavorwest.com/index.php/water-soluble-flavoring/glazed-doughnut.html","base":null,"density":1.0,"imageUrl":"","description":null,"description_raw":null,"short_description":null,"vendor_percentage":0.0,"vendor_description_raw":null,"vendor_description":null,"other_names":"","discontinued":false,"tags":{}},{"mix_id":2126734418727,"mix_sid":"r50arfvr","id":8483,"name":"Malt","vendor":{"name":"Flavor West","abbreviation":"FW","mix_id":2163807369996,"mix_sid":"rm1f1g5o"},"created_at":"2017-07-20T18:55:23.000-04:00","updated_at":"2019-02-26T10:22:28.000-05:00","deleted":null,"deleted_at":null,"recipe_count":16,"average_millipercent":607,"slug":"flavor-west-malt","confirmed":true,"rejected":false,"vendor_url":"http://flavorwest.com/index.php/water-soluble-flavoring/malt.html","base":null,"density":1.0,"imageUrl":"","description":null,"description_raw":null,"short_description":null,"vendor_percentage":0.0,"vendor_description_raw":null,"vendor_description":null,"other_names":"","discontinued":false,"tags":{}},{"mix_id":2131392084024,"mix_sid":"r75btdfc","id":8484,"name":"Malt Candy Balls","vendor":{"name":"Flavor West","abbreviation":"FW","mix_id":2163807369996,"mix_sid":"rm1f1g5o"},"created_at":"2017-07-20T18:55:23.000-04:00","updated_at":"2019-03-21T07:33:58.000-04:00","deleted":null,"deleted_at":null,"recipe_count":2,"average_millipercent":5200,"slug":"flavor-west-malt-candy-balls","confirmed":true,"rejected":false,"vendor_url":"http://flavorwest.com/index.php/water-soluble-flavoring/malt-candy.html","base":null,"density":1.0,"imageUrl":"","description":null,"description_raw":null,"short_description":null,"vendor_percentage":0.0,"vendor_description_raw":null,"vendor_description":null,"other_names":"","discontinued":false,"tags":{}},{"mix_id":2057578370317,"mix_sid":"q98l1bf1","id":8485,"name":"Mystery Flavor","vendor":{"name":"Flavor West","abbreviation":"FW","mix_id":2163807369996,"mix_sid":"rm1f1g5o"},"created_at":"2017-07-20T18:55:24.000-04:00","updated_at":"2019-05-17T03:30:06.000-04:00","deleted":null,"deleted_at":null,"recipe_count":1,"average_millipercent":15000,"slug":"flavor-west-mystery-flavor","confirmed":true,"rejected":false,"vendor_url":"http://flavorwest.com/index.php/water-soluble-flavoring/mystery-flavor.html","base":null,"density":1.0,"imageUrl":"","description":null,"description_raw":null,"short_description":null,"vendor_percentage":0.0,"vendor_description_raw":null,"vendor_description":null,"other_names":"","discontinued":false,"tags":{}},{"mix_id":2130737184674,"mix_sid":"r6uhwluq","id":8488,"name":"Rainbow Candy (Natural)","vendor":{"name":"Flavor West","abbreviation":"FW","mix_id":2163807369996,"mix_sid":"rm1f1g5o"},"created_at":"2017-07-20T18:55:26.000-04:00","updated_at":"2018-06-16T12:41:51.000-04:00","deleted":null,"deleted_at":null,"recipe_count":0,"average_millipercent":0,"slug":"flavor-west-rainbow-candy-natural","confirmed":true,"rejected":false,"vendor_url":"http://flavorwest.com/index.php/water-soluble-flavoring/rainbow-candy-natural.html","base":null,"density":1.0,"imageUrl":"","description":null,"description_raw":null,"short_description":null,"vendor_percentage":0.0,"vendor_description_raw":null,"vendor_description":null,"other_names":"","discontinued":false,"tags":{}},{"mix_id":2122892633764,"mix_sid":"r38rgnms","id":8489,"name":"S'mores","vendor":{"name":"Flavor West","abbreviation":"FW","mix_id":2163807369996,"mix_sid":"rm1f1g5o"},"created_at":"2017-07-20T18:55:28.000-04:00","updated_at":"2018-03-23T17:34:53.000-04:00","deleted":null,"deleted_at":null,"recipe_count":0,"average_millipercent":0,"slug":"flavor-west-s-mores","confirmed":true,"rejected":false,"vendor_url":"http://flavorwest.com/index.php/water-soluble-flavoring/s-mores.html","base":null,"density":1.0,"imageUrl":"","description":null,"description_raw":null,"short_description":null,"vendor_percentage":0.0,"vendor_description_raw":null,"vendor_description":null,"other_names":"","discontinued":false,"tags":{}},{"mix_id":2142183370085,"mix_sid":"rc3so31h","id":8490,"name":"Sprinkles","vendor":{"name":"Flavor West","abbreviation":"FW","mix_id":2163807369996,"mix_sid":"rm1f1g5o"},"created_at":"2017-07-20T18:55:28.000-04:00","updated_at":"2019-06-13T10:04:16.000-04:00","deleted":null,"deleted_at":null,"recipe_count":44,"average_millipercent":1764,"slug":"flavor-west-sprinkles","confirmed":true,"rejected":false,"vendor_url":"http://flavorwest.com/index.php/water-soluble-flavoring/sprinkles.html","base":null,"density":1.0,"imageUrl":"","description":null,"description_raw":null,"short_description":null,"vendor_percentage":0.0,"vendor_description_raw":null,"vendor_description":null,"other_names":"","discontinued":false,"tags":{}},{"mix_id":2162074975737,"mix_sid":"rl8rm86x","id":8491,"name":"Starburst Type","vendor":{"name":"Flavor West","abbreviation":"FW","mix_id":2163807369996,"mix_sid":"rm1f1g5o"},"created_at":"2017-07-20T18:55:29.000-04:00","updated_at":"2019-06-22T21:16:44.000-04:00","deleted":null,"deleted_at":null,"recipe_count":116,"average_millipercent":2002,"slug":"flavor-west-starburst-type","confirmed":true,"rejected":false,"vendor_url":"http://flavorwest.com/index.php/water-soluble-flavoring/starburst-type.html","base":null,"density":1.0,"imageUrl":"","description":null,"description_raw":null,"short_description":null,"vendor_percentage":0.0,"vendor_description_raw":null,"vendor_description":null,"other_names":"","discontinued":false,"tags":{}},{"mix_id":2117331659191,"mix_sid":"r0oslo6v","id":8492,"name":"Strawberry Milkshake","vendor":{"name":"Flavor West","abbreviation":"FW","mix_id":2163807369996,"mix_sid":"rm1f1g5o"},"created_at":"2017-07-20T18:55:29.000-04:00","updated_at":"2019-03-15T01:34:24.000-04:00","deleted":null,"deleted_at":null,"recipe_count":28,"average_millipercent":3697,"slug":"flavor-west-strawberry-milkshake","confirmed":true,"rejected":false,"vendor_url":"http://flavorwest.com/index.php/water-soluble-flavoring/strawberry-milkshake.html","base":null,"density":1.0,"imageUrl":"","description":null,"description_raw":null,"short_description":null,"vendor_percentage":0.0,"vendor_description_raw":null,"vendor_description":null,"other_names":"","discontinued":false,"tags":{}},{"mix_id":2075610093393,"mix_sid":"qhisnpzl","id":8494,"name":"Sunrise Menthol Tobacco","vendor":{"name":"Flavor West","abbreviation":"FW","mix_id":2163807369996,"mix_sid":"rm1f1g5o"},"created_at":"2017-07-20T18:55:30.000-04:00","updated_at":"2017-07-20T19:25:13.000-04:00","deleted":null,"deleted_at":null,"recipe_count":0,"average_millipercent":0,"slug":"flavor-west-sunrise-menthol-tobacco","confirmed":true,"rejected":false,"vendor_url":"http://flavorwest.com/index.php/water-soluble-flavoring/sunrise-menthol-tobacco.html","base":null,"density":1.0,"imageUrl":"","description":null,"description_raw":null,"short_description":null,"vendor_percentage":0.0,"vendor_description_raw":null,"vendor_description":null,"other_names":"","discontinued":false,"tags":{}},{"mix_id":2158776450486,"mix_sid":"rjq7rdti","id":8495,"name":"Toffee Bar","vendor":{"name":"Flavor West","abbreviation":"FW","mix_id":2163807369996,"mix_sid":"rm1f1g5o"},"created_at":"2017-07-20T18:55:31.000-04:00","updated_at":"2017-07-20T19:25:13.000-04:00","deleted":null,"deleted_at":null,"recipe_count":0,"average_millipercent":0,"slug":"flavor-west-toffee-bar","confirmed":true,"rejected":false,"vendor_url":"http://flavorwest.com/index.php/water-soluble-flavoring/toffee-bar.html","base":null,"density":1.0,"imageUrl":"","description":null,"description_raw":null,"short_description":null,"vendor_percentage":0.0,"vendor_description_raw":null,"vendor_description":null,"other_names":"","discontinued":false,"tags":{}},{"mix_id":2160371704150,"mix_sid":"rkglj7fa","id":8496,"name":"Waffle Cone","vendor":{"name":"Flavor West","abbreviation":"FW","mix_id":2163807369996,"mix_sid":"rm1f1g5o"},"created_at":"2017-07-20T18:55:32.000-04:00","updated_at":"2019-05-25T01:18:39.000-04:00","deleted":null,"deleted_at":null,"recipe_count":35,"average_millipercent":1872,"slug":"flavor-west-waffle-cone","confirmed":true,"rejected":false,"vendor_url":"http://flavorwest.com/index.php/water-soluble-flavoring/waffle-cone.html","base":null,"density":1.0,"imageUrl":"","description":null,"description_raw":null,"short_description":null,"vendor_percentage":0.0,"vendor_description_raw":null,"vendor_description":null,"other_names":"","discontinued":false,"tags":{}},{"mix_id":2150539229097,"mix_sid":"rfxzj549","id":8498,"name":"White Peach","vendor":{"name":"Flavor West","abbreviation":"FW","mix_id":2163807369996,"mix_sid":"rm1f1g5o"},"created_at":"2017-07-20T18:55:33.000-04:00","updated_at":"2019-04-05T01:34:41.000-04:00","deleted":null,"deleted_at":null,"recipe_count":3,"average_millipercent":867,"slug":"flavor-west-white-peach","confirmed":true,"rejected":false,"vendor_url":"http://flavorwest.com/index.php/water-soluble-flavoring/white-peach.html","base":null,"density":1.0,"imageUrl":"","description":null,"description_raw":null,"short_description":null,"vendor_percentage":0.0,"vendor_description_raw":null,"vendor_description":null,"other_names":"","discontinued":false,"tags":{}},{"mix_id":2045301539674,"mix_sid":"q3ljq89m","id":8499,"name":"Wild Berry Cobbler ala Mode","vendor":{"name":"Flavor West","abbreviation":"FW","mix_id":2163807369996,"mix_sid":"rm1f1g5o"},"created_at":"2017-07-20T18:55:34.000-04:00","updated_at":"2019-06-19T22:42:35.000-04:00","deleted":null,"deleted_at":null,"recipe_count":109,"average_millipercent":2652,"slug":"flavor-west-wild-berry-cobbler-ala-mode","confirmed":true,"rejected":false,"vendor_url":"http://flavorwest.com/index.php/water-soluble-flavoring/wild-berry-cobbler-ala-mode.html","base":null,"density":1.0,"imageUrl":"","description":null,"description_raw":null,"short_description":null,"vendor_percentage":0.0,"vendor_description_raw":null,"vendor_description":null,"other_names":"","discontinued":false,"tags":{}},{"mix_id":2073316059683,"mix_sid":"qgguum8z","id":8505,"name":"Tobacco Absolute Cuban Cigar","vendor":{"name":"Inawera","abbreviation":"INW","mix_id":2162065351688,"mix_sid":"rl8lvy88"},"created_at":"2017-07-22T15:35:15.000-04:00","updated_at":"2019-06-09T13:35:03.000-04:00","deleted":null,"deleted_at":null,"recipe_count":100,"average_millipercent":1867,"slug":"inawera-tobacco-absolute-cuban-cigar","confirmed":true,"rejected":false,"vendor_url":"http://www.inaweraflavours.com/en/do-it-yourself/693-tobacco-absolute-cuban-cigar-10-ml.html","base":null,"density":1.0,"imageUrl":"","description":null,"description_raw":null,"short_description":null,"vendor_percentage":0.0,"vendor_description_raw":null,"vendor_description":null,"other_names":"","discontinued":false,"tags":{}},{"mix_id":2045602377300,"mix_sid":"q3qiu82c","id":8506,"name":"Tobacco Absolute Virginia","vendor":{"name":"Inawera","abbreviation":"INW","mix_id":2162065351688,"mix_sid":"rl8lvy88"},"created_at":"2017-07-22T15:36:03.000-04:00","updated_at":"2019-06-18T10:52:03.000-04:00","deleted":null,"deleted_at":null,"recipe_count":34,"average_millipercent":1215,"slug":"inawera-tobacco-absolute-virginia","confirmed":true,"rejected":false,"vendor_url":"http://www.inaweraflavours.com/en/do-it-yourself/691-tobacco-absolute-virginia-10-ml.html","base":null,"density":1.0,"imageUrl":"","description":null,"description_raw":null,"short_description":null,"vendor_percentage":0.0,"vendor_description_raw":null,"vendor_description":null,"other_names":"","discontinued":false,"tags":{}},{"mix_id":2127201215846,"mix_sid":"r580oiue","id":8507,"name":"PE Tobacco","vendor":{"name":"Hangsen","abbreviation":"HS","mix_id":2051660231669,"mix_sid":"q6ipj2et"},"created_at":"2017-07-22T15:37:58.000-04:00","updated_at":"2017-07-22T16:12:14.000-04:00","deleted":null,"deleted_at":null,"recipe_count":0,"average_millipercent":0,"slug":"hangsen-pe-tobacco","confirmed":true,"rejected":false,"vendor_url":"","base":null,"density":1.0,"imageUrl":"","description":null,"description_raw":null,"short_description":null,"vendor_percentage":0.0,"vendor_description_raw":null,"vendor_description":null,"other_names":"","discontinued":false,"tags":{}},{"mix_id":2075889037176,"mix_sid":"qhneqge0","id":8508,"name":"SE Tobacco","vendor":{"name":"Hangsen","abbreviation":"HS","mix_id":2051660231669,"mix_sid":"q6ipj2et"},"created_at":"2017-07-22T15:38:07.000-04:00","updated_at":"2019-01-08T20:40:34.000-05:00","deleted":null,"deleted_at":null,"recipe_count":4,"average_millipercent":2375,"slug":"hangsen-se-tobacco","confirmed":true,"rejected":false,"vendor_url":"","base":null,"density":1.0,"imageUrl":"","description":null,"description_raw":null,"short_description":null,"vendor_percentage":0.0,"vendor_description_raw":null,"vendor_description":null,"other_names":"","discontinued":false,"tags":{}},{"mix_id":2126034445580,"mix_sid":"r4oq0l58","id":8510,"name":"Apple Pie","vendor":{"name":"Liquid Nicotine","abbreviation":"LNW","mix_id":2155601472378,"mix_sid":"ri9pgl16"},"created_at":"2017-07-22T20:08:12.000-04:00","updated_at":"2017-07-22T22:12:22.000-04:00","deleted":null,"deleted_at":null,"recipe_count":0,"average_millipercent":0,"slug":"liquid-nicotine-apple-pie","confirmed":true,"rejected":false,"vendor_url":"https://liquidnicotinewholesalers.com/lnw-apple-pie.html","base":null,"density":1.0,"imageUrl":"","description":null,"description_raw":null,"short_description":null,"vendor_percentage":0.0,"vendor_description_raw":null,"vendor_description":null,"other_names":"","discontinued":false,"tags":{}},{"mix_id":2068823904225,"mix_sid":"qeekc4wx","id":8511,"name":"Blueberry","vendor":{"name":"Liquid Nicotine","abbreviation":"LNW","mix_id":2155601472378,"mix_sid":"ri9pgl16"},"created_at":"2017-07-22T20:08:12.000-04:00","updated_at":"2017-07-22T22:12:23.000-04:00","deleted":null,"deleted_at":null,"recipe_count":0,"average_millipercent":0,"slug":"liquid-nicotine-blueberry","confirmed":true,"rejected":false,"vendor_url":"https://liquidnicotinewholesalers.com/lnw-blueberry.html","base":null,"density":1.0,"imageUrl":"","description":null,"description_raw":null,"short_description":null,"vendor_percentage":0.0,"vendor_description_raw":null,"vendor_description":null,"other_names":"","discontinued":false,"tags":{}},{"mix_id":2111594819563,"mix_sid":"qy1x1aej","id":8512,"name":"Brownie","vendor":{"name":"Liquid Nicotine","abbreviation":"LNW","mix_id":2155601472378,"mix_sid":"ri9pgl16"},"created_at":"2017-07-22T20:08:13.000-04:00","updated_at":"2017-07-22T22:12:23.000-04:00","deleted":null,"deleted_at":null,"recipe_count":0,"average_millipercent":0,"slug":"liquid-nicotine-brownie","confirmed":true,"rejected":false,"vendor_url":"https://liquidnicotinewholesalers.com/lnw-brownie.html","base":null,"density":1.0,"imageUrl":"","description":null,"description_raw":null,"short_description":null,"vendor_percentage":0.0,"vendor_description_raw":null,"vendor_description":null,"other_names":"","discontinued":false,"tags":{}},{"mix_id":2146924610154,"mix_sid":"rea7hbai","id":8513,"name":"Cappuccino","vendor":{"name":"Liquid Nicotine","abbreviation":"LNW","mix_id":2155601472378,"mix_sid":"ri9pgl16"},"created_at":"2017-07-22T20:08:13.000-04:00","updated_at":"2017-07-22T22:12:24.000-04:00","deleted":null,"deleted_at":null,"recipe_count":0,"average_millipercent":0,"slug":"liquid-nicotine-cappuccino","confirmed":true,"rejected":false,"vendor_url":"https://liquidnicotinewholesalers.com/lnw-cappuccino.html","base":null,"density":1.0,"imageUrl":"","description":null,"description_raw":null,"short_description":null,"vendor_percentage":0.0,"vendor_description_raw":null,"vendor_description":null,"other_names":"","discontinued":false,"tags":{}},{"mix_id":2160580187824,"mix_sid":"rkk1nqgg","id":8514,"name":"Caramel Mocha","vendor":{"name":"Liquid Nicotine","abbreviation":"LNW","mix_id":2155601472378,"mix_sid":"ri9pgl16"},"created_at":"2017-07-22T20:08:14.000-04:00","updated_at":"2017-07-22T22:12:24.000-04:00","deleted":null,"deleted_at":null,"recipe_count":0,"average_millipercent":0,"slug":"liquid-nicotine-caramel-mocha","confirmed":true,"rejected":false,"vendor_url":"https://liquidnicotinewholesalers.com/lnw-caramel-mocha.html","base":null,"density":1.0,"imageUrl":"","description":null,"description_raw":null,"short_description":null,"vendor_percentage":0.0,"vendor_description_raw":null,"vendor_description":null,"other_names":"","discontinued":false,"tags":{}},{"mix_id":2074146825480,"mix_sid":"qgulgt8o","id":8515,"name":"Chocolate Mint","vendor":{"name":"Liquid Nicotine","abbreviation":"LNW","mix_id":2155601472378,"mix_sid":"ri9pgl16"},"created_at":"2017-07-22T20:08:14.000-04:00","updated_at":"2017-07-22T22:12:24.000-04:00","deleted":null,"deleted_at":null,"recipe_count":0,"average_millipercent":0,"slug":"liquid-nicotine-chocolate-mint","confirmed":true,"rejected":false,"vendor_url":"https://liquidnicotinewholesalers.com/lnw-chocolate-mint.html","base":null,"density":1.0,"imageUrl":"","description":null,"description_raw":null,"short_description":null,"vendor_percentage":0.0,"vendor_description_raw":null,"vendor_description":null,"other_names":"","discontinued":false,"tags":{}},{"mix_id":2046143275510,"mix_sid":"q3zgvjsm","id":8516,"name":"Graham Cracker","vendor":{"name":"Liquid Nicotine","abbreviation":"LNW","mix_id":2155601472378,"mix_sid":"ri9pgl16"},"created_at":"2017-07-22T20:08:14.000-04:00","updated_at":"2017-07-22T22:12:25.000-04:00","deleted":null,"deleted_at":null,"recipe_count":0,"average_millipercent":0,"slug":"liquid-nicotine-graham-cracker","confirmed":true,"rejected":false,"vendor_url":"https://liquidnicotinewholesalers.com/lnw-graham-cracker.html","base":null,"density":1.0,"imageUrl":"","description":null,"description_raw":null,"short_description":null,"vendor_percentage":0.0,"vendor_description_raw":null,"vendor_description":null,"other_names":"","discontinued":false,"tags":{}},{"mix_id":2140360818444,"mix_sid":"rb9nkh70","id":8517,"name":"Grape","vendor":{"name":"Liquid Nicotine","abbreviation":"LNW","mix_id":2155601472378,"mix_sid":"ri9pgl16"},"created_at":"2017-07-22T20:08:15.000-04:00","updated_at":"2017-07-22T22:12:25.000-04:00","deleted":null,"deleted_at":null,"recipe_count":0,"average_millipercent":0,"slug":"liquid-nicotine-grape","confirmed":true,"rejected":false,"vendor_url":"https://liquidnicotinewholesalers.com/lnw-grape.html","base":null,"density":1.0,"imageUrl":"","description":null,"description_raw":null,"short_description":null,"vendor_percentage":0.0,"vendor_description_raw":null,"vendor_description":null,"other_names":"","discontinued":false,"tags":{}},{"mix_id":2101838981711,"mix_sid":"qtkkntqn","id":8518,"name":"Loops","vendor":{"name":"Liquid Nicotine","abbreviation":"LNW","mix_id":2155601472378,"mix_sid":"ri9pgl16"},"created_at":"2017-07-22T20:08:15.000-04:00","updated_at":"2019-04-20T23:35:43.000-04:00","deleted":null,"deleted_at":null,"recipe_count":0,"average_millipercent":0,"slug":"liquid-nicotine-loops","confirmed":true,"rejected":false,"vendor_url":"https://liquidnicotinewholesalers.com/lnw-loops.html","base":null,"density":1.0,"imageUrl":"","description":null,"description_raw":null,"short_description":null,"vendor_percentage":0.0,"vendor_description_raw":null,"vendor_description":null,"other_names":"","discontinued":false,"tags":{}},{"mix_id":2067607946985,"mix_sid":"qdugdyax","id":8519,"name":"Neopolitan","vendor":{"name":"Liquid Nicotine","abbreviation":"LNW","mix_id":2155601472378,"mix_sid":"ri9pgl16"},"created_at":"2017-07-22T20:08:16.000-04:00","updated_at":"2017-07-22T22:12:26.000-04:00","deleted":null,"deleted_at":null,"recipe_count":0,"average_millipercent":0,"slug":"liquid-nicotine-neopolitan","confirmed":true,"rejected":false,"vendor_url":"https://liquidnicotinewholesalers.com/lnw-neopolitan.html","base":null,"density":1.0,"imageUrl":"","description":null,"description_raw":null,"short_description":null,"vendor_percentage":0.0,"vendor_description_raw":null,"vendor_description":null,"other_names":"","discontinued":false,"tags":{}},{"mix_id":2108235311608,"mix_sid":"qwicvdh4","id":8520,"name":"Orange Cream","vendor":{"name":"Liquid Nicotine","abbreviation":"LNW","mix_id":2155601472378,"mix_sid":"ri9pgl16"},"created_at":"2017-07-22T20:08:16.000-04:00","updated_at":"2017-07-22T22:12:27.000-04:00","deleted":null,"deleted_at":null,"recipe_count":0,"average_millipercent":0,"slug":"liquid-nicotine-orange-cream","confirmed":true,"rejected":false,"vendor_url":"https://liquidnicotinewholesalers.com/lnw-orange-cream.html","base":null,"density":1.0,"imageUrl":"","description":null,"description_raw":null,"short_description":null,"vendor_percentage":0.0,"vendor_description_raw":null,"vendor_description":null,"other_names":"","discontinued":false,"tags":{}},{"mix_id":2085213961228,"mix_sid":"qlxmjxu4","id":8521,"name":"Pineapple","vendor":{"name":"Liquid Nicotine","abbreviation":"LNW","mix_id":2155601472378,"mix_sid":"ri9pgl16"},"created_at":"2017-07-22T20:08:16.000-04:00","updated_at":"2017-07-22T22:12:27.000-04:00","deleted":null,"deleted_at":null,"recipe_count":0,"average_millipercent":0,"slug":"liquid-nicotine-pineapple","confirmed":true,"rejected":false,"vendor_url":"https://liquidnicotinewholesalers.com/lnw-pineapple.html","base":null,"density":1.0,"imageUrl":"","description":null,"description_raw":null,"short_description":null,"vendor_percentage":0.0,"vendor_description_raw":null,"vendor_description":null,"other_names":"","discontinued":false,"tags":{}},{"mix_id":2079412789324,"mix_sid":"qj9oooy4","id":8522,"name":"Rainbow Sherbet","vendor":{"name":"Liquid Nicotine","abbreviation":"LNW","mix_id":2155601472378,"mix_sid":"ri9pgl16"},"created_at":"2017-07-22T20:08:17.000-04:00","updated_at":"2017-07-22T22:12:28.000-04:00","deleted":null,"deleted_at":null,"recipe_count":0,"average_millipercent":0,"slug":"liquid-nicotine-rainbow-sherbet","confirmed":true,"rejected":false,"vendor_url":"https://liquidnicotinewholesalers.com/lnw-rainbow-sherbet.html","base":null,"density":1.0,"imageUrl":"","description":null,"description_raw":null,"short_description":null,"vendor_percentage":0.0,"vendor_description_raw":null,"vendor_description":null,"other_names":"","discontinued":false,"tags":{}},{"mix_id":2085182532130,"mix_sid":"qlx3uazm","id":8523,"name":"Rice Krispy Treat","vendor":{"name":"Liquid Nicotine","abbreviation":"LNW","mix_id":2155601472378,"mix_sid":"ri9pgl16"},"created_at":"2017-07-22T20:08:17.000-04:00","updated_at":"2017-07-22T22:12:28.000-04:00","deleted":null,"deleted_at":null,"recipe_count":0,"average_millipercent":0,"slug":"liquid-nicotine-rice-krispy-treat","confirmed":true,"rejected":false,"vendor_url":"https://liquidnicotinewholesalers.com/lnw-rice-krispy-treat.html","base":null,"density":1.0,"imageUrl":"","description":null,"description_raw":null,"short_description":null,"vendor_percentage":0.0,"vendor_description_raw":null,"vendor_description":null,"other_names":"","discontinued":false,"tags":{}},{"mix_id":2055276258390,"mix_sid":"q86if2hi","id":8524,"name":"Smoothie","vendor":{"name":"Liquid Nicotine","abbreviation":"LNW","mix_id":2155601472378,"mix_sid":"ri9pgl16"},"created_at":"2017-07-22T20:08:18.000-04:00","updated_at":"2017-07-22T22:12:29.000-04:00","deleted":null,"deleted_at":null,"recipe_count":0,"average_millipercent":0,"slug":"liquid-nicotine-smoothie","confirmed":true,"rejected":false,"vendor_url":"https://liquidnicotinewholesalers.com/lnw-smoothie.html","base":null,"density":1.0,"imageUrl":"","description":null,"description_raw":null,"short_description":null,"vendor_percentage":0.0,"vendor_description_raw":null,"vendor_description":null,"other_names":"","discontinued":false,"tags":{}},{"mix_id":2134828611917,"mix_sid":"r8q5u3bh","id":8525,"name":"Strawberry Banana","vendor":{"name":"Liquid Nicotine","abbreviation":"LNW","mix_id":2155601472378,"mix_sid":"ri9pgl16"},"created_at":"2017-07-22T20:08:18.000-04:00","updated_at":"2017-07-22T22:12:29.000-04:00","deleted":null,"deleted_at":null,"recipe_count":0,"average_millipercent":0,"slug":"liquid-nicotine-strawberry-banana","confirmed":true,"rejected":false,"vendor_url":"https://liquidnicotinewholesalers.com/lnw-strawberry-banana.html","base":null,"density":1.0,"imageUrl":"","description":null,"description_raw":null,"short_description":null,"vendor_percentage":0.0,"vendor_description_raw":null,"vendor_description":null,"other_names":"","discontinued":false,"tags":{}},{"mix_id":2117877203895,"mix_sid":"r0xtel6f","id":8526,"name":"Swedish Gummies","vendor":{"name":"Liquid Nicotine","abbreviation":"LNW","mix_id":2155601472378,"mix_sid":"ri9pgl16"},"created_at":"2017-07-22T20:08:18.000-04:00","updated_at":"2017-07-22T22:12:30.000-04:00","deleted":null,"deleted_at":null,"recipe_count":0,"average_millipercent":0,"slug":"liquid-nicotine-swedish-gummies","confirmed":true,"rejected":false,"vendor_url":"https://liquidnicotinewholesalers.com/lnw-swedish-gummies.html","base":null,"density":1.0,"imageUrl":"","description":null,"description_raw":null,"short_description":null,"vendor_percentage":0.0,"vendor_description_raw":null,"vendor_description":null,"other_names":"","discontinued":false,"tags":{}},{"mix_id":2113292945643,"mix_sid":"qyu020vf","id":8527,"name":"Sweet Cream","vendor":{"name":"Liquid Nicotine","abbreviation":"LNW","mix_id":2155601472378,"mix_sid":"ri9pgl16"},"created_at":"2017-07-22T20:08:19.000-04:00","updated_at":"2017-07-22T22:12:30.000-04:00","deleted":null,"deleted_at":null,"recipe_count":0,"average_millipercent":0,"slug":"liquid-nicotine-sweet-cream","confirmed":true,"rejected":false,"vendor_url":"https://liquidnicotinewholesalers.com/lnw-sweet-cream.html","base":null,"density":1.0,"imageUrl":"","description":null,"description_raw":null,"short_description":null,"vendor_percentage":0.0,"vendor_description_raw":null,"vendor_description":null,"other_names":"","discontinued":false,"tags":{}},{"mix_id":2059911083607,"mix_sid":"qab5vgif","id":8528,"name":"Tropical Punch","vendor":{"name":"Liquid Nicotine","abbreviation":"LNW","mix_id":2155601472378,"mix_sid":"ri9pgl16"},"created_at":"2017-07-22T20:08:19.000-04:00","updated_at":"2017-07-22T22:12:31.000-04:00","deleted":null,"deleted_at":null,"recipe_count":0,"average_millipercent":0,"slug":"liquid-nicotine-tropical-punch","confirmed":true,"rejected":false,"vendor_url":"https://liquidnicotinewholesalers.com/lnw-tropical-punch.html","base":null,"density":1.0,"imageUrl":"","description":null,"description_raw":null,"short_description":null,"vendor_percentage":0.0,"vendor_description_raw":null,"vendor_description":null,"other_names":"","discontinued":false,"tags":{}},{"mix_id":2097008239024,"mix_sid":"qrcok8ts","id":8529,"name":"Vanilla Custard","vendor":{"name":"Liquid Nicotine","abbreviation":"LNW","mix_id":2155601472378,"mix_sid":"ri9pgl16"},"created_at":"2017-07-22T20:08:20.000-04:00","updated_at":"2019-06-12T14:58:59.000-04:00","deleted":null,"deleted_at":null,"recipe_count":6,"average_millipercent":2584,"slug":"liquid-nicotine-vanilla-custard","confirmed":true,"rejected":false,"vendor_url":"https://liquidnicotinewholesalers.com/lnw-vanilla-custard.html","base":null,"density":1.0,"imageUrl":"","description":null,"description_raw":null,"short_description":null,"vendor_percentage":0.0,"vendor_description_raw":null,"vendor_description":null,"other_names":"","discontinued":false,"tags":{}},{"mix_id":2085529175193,"mix_sid":"qm2u82hl","id":8530,"name":"Vanilla Ice Cream","vendor":{"name":"Liquid Nicotine","abbreviation":"LNW","mix_id":2155601472378,"mix_sid":"ri9pgl16"},"created_at":"2017-07-22T20:08:20.000-04:00","updated_at":"2017-07-22T22:12:32.000-04:00","deleted":null,"deleted_at":null,"recipe_count":0,"average_millipercent":0,"slug":"liquid-nicotine-vanilla-ice-cream","confirmed":true,"rejected":false,"vendor_url":"https://liquidnicotinewholesalers.com/lnw-vanilla-ice-cream.html","base":null,"density":1.0,"imageUrl":"","description":null,"description_raw":null,"short_description":null,"vendor_percentage":0.0,"vendor_description_raw":null,"vendor_description":null,"other_names":"","discontinued":false,"tags":{}},{"mix_id":2064883589049,"mix_sid":"qcledi9l","id":8535,"name":"Ice -- Original","vendor":{"name":"Delosi","abbreviation":"DF","mix_id":2054201082047,"mix_sid":"q7oqab3z"},"created_at":"2017-08-03T07:30:04.000-04:00","updated_at":"2018-10-29T14:49:04.000-04:00","deleted":null,"deleted_at":null,"recipe_count":2,"average_millipercent":1500,"slug":"delosi-ice-original","confirmed":true,"rejected":false,"vendor_url":"http://www.delosi.com/flavoring/additives-and-spices/ice-original-concentrated-additive.html","base":null,"density":1.0,"imageUrl":"","description":null,"description_raw":null,"short_description":null,"vendor_percentage":0.0,"vendor_description_raw":null,"vendor_description":null,"other_names":"","discontinued":false,"tags":{}},{"mix_id":2059600682649,"mix_sid":"qa612hll","id":8543,"name":"Tiramisu","vendor":{"name":"Jungle Flavors","abbreviation":"JF","mix_id":2103294077151,"mix_sid":"qu8mzkkf"},"created_at":"2017-08-24T01:33:01.000-04:00","updated_at":"2017-08-24T04:14:23.000-04:00","deleted":null,"deleted_at":null,"recipe_count":0,"average_millipercent":0,"slug":"jungle-flavors-tiramisu","confirmed":true,"rejected":false,"vendor_url":"http://www.ecigexpress.com/shop/diy-e-liquid/diy-e-liquid-flavors/jungle-flavors/fruit-and-sweet/tiramisu-by-jungle-flavors.html","base":null,"density":1.0,"imageUrl":"","description":null,"description_raw":null,"short_description":null,"vendor_percentage":0.0,"vendor_description_raw":null,"vendor_description":null,"other_names":"","discontinued":false,"tags":{}},{"mix_id":2119655630345,"mix_sid":"r1r88ft5","id":8548,"name":"Amaretto Sour","vendor":{"name":"Flavorah","abbreviation":"FLV","mix_id":2095493645177,"mix_sid":"qqnmt8qh"},"created_at":"2017-08-31T22:30:01.000-04:00","updated_at":"2019-04-15T12:44:01.000-04:00","deleted":null,"deleted_at":null,"recipe_count":9,"average_millipercent":1500,"slug":"flavorah-amaretto-sour","confirmed":true,"rejected":false,"vendor_url":null,"base":null,"density":1.0,"imageUrl":"","description":null,"description_raw":null,"short_description":null,"vendor_percentage":0.0,"vendor_description_raw":null,"vendor_description":null,"other_names":"","discontinued":false,"tags":{}},{"mix_id":2120399376183,"mix_sid":"r23j1hrr","id":8549,"name":"Apricot","vendor":{"name":"Flavorah","abbreviation":"FLV","mix_id":2095493645177,"mix_sid":"qqnmt8qh"},"created_at":"2017-08-31T22:30:02.000-04:00","updated_at":"2019-06-14T21:20:51.000-04:00","deleted":null,"deleted_at":null,"recipe_count":71,"average_millipercent":1600,"slug":"flavorah-apricot","confirmed":true,"rejected":false,"vendor_url":null,"base":null,"density":1.0,"imageUrl":"","description":null,"description_raw":null,"short_description":null,"vendor_percentage":0.0,"vendor_description_raw":null,"vendor_description":null,"other_names":"","discontinued":false,"tags":{}},{"mix_id":2082891557065,"mix_sid":"qkv7urbd","id":8550,"name":"Blackberry Blossom","vendor":{"name":"Flavorah","abbreviation":"FLV","mix_id":2095493645177,"mix_sid":"qqnmt8qh"},"created_at":"2017-08-31T22:30:02.000-04:00","updated_at":"2019-06-15T19:55:59.000-04:00","deleted":null,"deleted_at":null,"recipe_count":26,"average_millipercent":1089,"slug":"flavorah-blackberry-blossom","confirmed":true,"rejected":false,"vendor_url":null,"base":null,"density":1.0,"imageUrl":"","description":null,"description_raw":null,"short_description":null,"vendor_percentage":0.0,"vendor_description_raw":null,"vendor_description":null,"other_names":"","discontinued":false,"tags":{}},{"mix_id":2075437493711,"mix_sid":"qhfxwb7z","id":8551,"name":"Brulee","vendor":{"name":"Flavorah","abbreviation":"FLV","mix_id":2095493645177,"mix_sid":"qqnmt8qh"},"created_at":"2017-08-31T22:30:03.000-04:00","updated_at":"2019-06-03T12:02:02.000-04:00","deleted":null,"deleted_at":null,"recipe_count":16,"average_millipercent":1391,"slug":"flavorah-brulee","confirmed":true,"rejected":false,"vendor_url":null,"base":null,"density":1.0,"imageUrl":"","description":null,"description_raw":null,"short_description":null,"vendor_percentage":0.0,"vendor_description_raw":null,"vendor_description":null,"other_names":"","discontinued":false,"tags":{}},{"mix_id":2072066564141,"mix_sid":"qfw6xlbh","id":8552,"name":"Carrot","vendor":{"name":"Flavorah","abbreviation":"FLV","mix_id":2095493645177,"mix_sid":"qqnmt8qh"},"created_at":"2017-08-31T22:30:03.000-04:00","updated_at":"2019-06-06T21:51:09.000-04:00","deleted":null,"deleted_at":null,"recipe_count":39,"average_millipercent":1362,"slug":"flavorah-carrot","confirmed":true,"rejected":false,"vendor_url":null,"base":null,"density":1.0,"imageUrl":"","description":null,"description_raw":null,"short_description":null,"vendor_percentage":0.0,"vendor_description_raw":null,"vendor_description":null,"other_names":"","discontinued":false,"tags":{}},{"mix_id":2158412700553,"mix_sid":"rjk76ykp","id":8553,"name":"Cherry Blossom","vendor":{"name":"Flavorah","abbreviation":"FLV","mix_id":2095493645177,"mix_sid":"qqnmt8qh"},"created_at":"2017-08-31T22:30:04.000-04:00","updated_at":"2019-06-18T15:52:53.000-04:00","deleted":null,"deleted_at":null,"recipe_count":17,"average_millipercent":662,"slug":"flavorah-cherry-blossom","confirmed":true,"rejected":false,"vendor_url":null,"base":null,"density":1.0,"imageUrl":"","description":null,"description_raw":null,"short_description":null,"vendor_percentage":0.0,"vendor_description_raw":null,"vendor_description":null,"other_names":"","discontinued":false,"tags":{}},{"mix_id":2054569466070,"mix_sid":"q7utm21i","id":8554,"name":"Graham Cracker","vendor":{"name":"Flavorah","abbreviation":"FLV","mix_id":2095493645177,"mix_sid":"qqnmt8qh"},"created_at":"2017-08-31T22:30:04.000-04:00","updated_at":"2019-06-17T14:54:01.000-04:00","deleted":null,"deleted_at":null,"recipe_count":260,"average_millipercent":1610,"slug":"flavorah-graham-cracker","confirmed":true,"rejected":false,"vendor_url":null,"base":null,"density":1.0,"imageUrl":"","description":null,"description_raw":null,"short_description":null,"vendor_percentage":0.0,"vendor_description_raw":null,"vendor_description":null,"other_names":"","discontinued":false,"tags":{}},{"mix_id":2077693526168,"mix_sid":"qih92x08","id":8555,"name":"Granola","vendor":{"name":"Flavorah","abbreviation":"FLV","mix_id":2095493645177,"mix_sid":"qqnmt8qh"},"created_at":"2017-08-31T22:30:04.000-04:00","updated_at":"2019-06-22T00:04:20.000-04:00","deleted":null,"deleted_at":null,"recipe_count":116,"average_millipercent":891,"slug":"flavorah-granola","confirmed":true,"rejected":false,"vendor_url":null,"base":null,"density":1.0,"imageUrl":"","description":null,"description_raw":null,"short_description":null,"vendor_percentage":0.0,"vendor_description_raw":null,"vendor_description":null,"other_names":"","discontinued":false,"tags":{}},{"mix_id":2115635278774,"mix_sid":"qzwqmcom","id":8556,"name":"Hazelnut","vendor":{"name":"Flavorah","abbreviation":"FLV","mix_id":2095493645177,"mix_sid":"qqnmt8qh"},"created_at":"2017-08-31T22:30:05.000-04:00","updated_at":"2019-05-23T09:20:22.000-04:00","deleted":null,"deleted_at":null,"recipe_count":2,"average_millipercent":350,"slug":"flavorah-hazelnut","confirmed":true,"rejected":false,"vendor_url":null,"base":null,"density":1.0,"imageUrl":"","description":null,"description_raw":null,"short_description":null,"vendor_percentage":0.0,"vendor_description_raw":null,"vendor_description":null,"other_names":"","discontinued":false,"tags":{}},{"mix_id":2051570621157,"mix_sid":"q6h86ehx","id":8557,"name":"Lembas Bread","vendor":{"name":"Flavorah","abbreviation":"FLV","mix_id":2095493645177,"mix_sid":"qqnmt8qh"},"created_at":"2017-08-31T22:30:05.000-04:00","updated_at":"2019-02-28T18:46:07.000-05:00","deleted":null,"deleted_at":null,"recipe_count":51,"average_millipercent":1667,"slug":"flavorah-lembas-bread","confirmed":true,"rejected":false,"vendor_url":null,"base":null,"density":1.0,"imageUrl":"","description":null,"description_raw":null,"short_description":null,"vendor_percentage":0.0,"vendor_description_raw":null,"vendor_description":null,"other_names":"","discontinued":false,"tags":{}},{"mix_id":2119643859819,"mix_sid":"r1r185m3","id":8558,"name":"Morning Mimosa","vendor":{"name":"Flavorah","abbreviation":"FLV","mix_id":2095493645177,"mix_sid":"qqnmt8qh"},"created_at":"2017-08-31T22:30:06.000-04:00","updated_at":"2019-06-13T16:08:32.000-04:00","deleted":null,"deleted_at":null,"recipe_count":47,"average_millipercent":1162,"slug":"flavorah-morning-mimosa","confirmed":true,"rejected":false,"vendor_url":null,"base":null,"density":1.0,"imageUrl":"","description":null,"description_raw":null,"short_description":null,"vendor_percentage":0.0,"vendor_description_raw":null,"vendor_description":null,"other_names":"","discontinued":false,"tags":{}},{"mix_id":2073129621315,"mix_sid":"qgdrulhf","id":8559,"name":"Moscato","vendor":{"name":"Flavorah","abbreviation":"FLV","mix_id":2095493645177,"mix_sid":"qqnmt8qh"},"created_at":"2017-08-31T22:30:06.000-04:00","updated_at":"2019-06-15T15:16:25.000-04:00","deleted":null,"deleted_at":null,"recipe_count":64,"average_millipercent":1293,"slug":"flavorah-muscato","confirmed":true,"rejected":false,"vendor_url":null,"base":null,"density":1.0,"imageUrl":"","description":null,"description_raw":null,"short_description":null,"vendor_percentage":0.0,"vendor_description_raw":null,"vendor_description":null,"other_names":"","discontinued":false,"tags":{}},{"mix_id":2094558515754,"mix_sid":"qq862696","id":8560,"name":"Nectarine","vendor":{"name":"Flavorah","abbreviation":"FLV","mix_id":2095493645177,"mix_sid":"qqnmt8qh"},"created_at":"2017-08-31T22:30:06.000-04:00","updated_at":"2019-06-21T23:12:50.000-04:00","deleted":null,"deleted_at":null,"recipe_count":22,"average_millipercent":1032,"slug":"flavorah-nectarine","confirmed":true,"rejected":false,"vendor_url":null,"base":null,"density":1.0,"imageUrl":"","description":null,"description_raw":null,"short_description":null,"vendor_percentage":0.0,"vendor_description_raw":null,"vendor_description":null,"other_names":"","discontinued":false,"tags":{}},{"mix_id":2079238039772,"mix_sid":"qj6sn7bw","id":8561,"name":"Oak Barrel","vendor":{"name":"Flavorah","abbreviation":"FLV","mix_id":2095493645177,"mix_sid":"qqnmt8qh"},"created_at":"2017-08-31T22:30:07.000-04:00","updated_at":"2019-05-25T07:21:38.000-04:00","deleted":null,"deleted_at":null,"recipe_count":58,"average_millipercent":1004,"slug":"flavorah-oak-barrel","confirmed":true,"rejected":false,"vendor_url":null,"base":null,"density":1.0,"imageUrl":"","description":null,"description_raw":null,"short_description":null,"vendor_percentage":0.0,"vendor_description_raw":null,"vendor_description":null,"other_names":"","discontinued":false,"tags":{}},{"mix_id":2064715046867,"mix_sid":"qcim12ab","id":8562,"name":"Pastry Zest","vendor":{"name":"Flavorah","abbreviation":"FLV","mix_id":2095493645177,"mix_sid":"qqnmt8qh"},"created_at":"2017-08-31T22:30:07.000-04:00","updated_at":"2019-06-18T23:59:05.000-04:00","deleted":null,"deleted_at":null,"recipe_count":139,"average_millipercent":1013,"slug":"flavorah-pastry-zest","confirmed":true,"rejected":false,"vendor_url":null,"base":null,"density":1.0,"imageUrl":"","description":null,"description_raw":null,"short_description":null,"vendor_percentage":0.0,"vendor_description_raw":null,"vendor_description":null,"other_names":"","discontinued":false,"tags":{}},{"mix_id":2165096012609,"mix_sid":"rmmq9j5t","id":8563,"name":"Peppermint","vendor":{"name":"Flavorah","abbreviation":"FLV","mix_id":2095493645177,"mix_sid":"qqnmt8qh"},"created_at":"2017-08-31T22:30:08.000-04:00","updated_at":"2019-06-17T17:56:08.000-04:00","deleted":null,"deleted_at":null,"recipe_count":56,"average_millipercent":936,"slug":"flavorah-peppermint","confirmed":true,"rejected":false,"vendor_url":null,"base":null,"density":1.0,"imageUrl":"","description":null,"description_raw":null,"short_description":null,"vendor_percentage":0.0,"vendor_description_raw":null,"vendor_description":null,"other_names":"","discontinued":false,"tags":{}},{"mix_id":2141177763123,"mix_sid":"rbn5yfqr","id":8564,"name":"Popcorn","vendor":{"name":"Flavorah","abbreviation":"FLV","mix_id":2095493645177,"mix_sid":"qqnmt8qh"},"created_at":"2017-08-31T22:30:08.000-04:00","updated_at":"2019-06-18T13:50:14.000-04:00","deleted":null,"deleted_at":null,"recipe_count":285,"average_millipercent":898,"slug":"flavorah-popcorn","confirmed":true,"rejected":false,"vendor_url":null,"base":null,"density":1.0,"imageUrl":"","description":null,"description_raw":null,"short_description":null,"vendor_percentage":0.0,"vendor_description_raw":null,"vendor_description":null,"other_names":"","discontinued":false,"tags":{}},{"mix_id":2126413126651,"mix_sid":"r4uzh1bv","id":8565,"name":"Pucker","vendor":{"name":"Flavorah","abbreviation":"FLV","mix_id":2095493645177,"mix_sid":"qqnmt8qh"},"created_at":"2017-08-31T22:30:08.000-04:00","updated_at":"2019-06-18T07:14:31.000-04:00","deleted":null,"deleted_at":null,"recipe_count":36,"average_millipercent":576,"slug":"flavorah-pucker","confirmed":true,"rejected":false,"vendor_url":null,"base":null,"density":1.0,"imageUrl":"","description":null,"description_raw":null,"short_description":null,"vendor_percentage":0.0,"vendor_description_raw":null,"vendor_description":null,"other_names":"","discontinued":false,"tags":{}},{"mix_id":2120072451789,"mix_sid":"r1y4edal","id":8566,"name":"Red Velvet","vendor":{"name":"Flavorah","abbreviation":"FLV","mix_id":2095493645177,"mix_sid":"qqnmt8qh"},"created_at":"2017-08-31T22:30:09.000-04:00","updated_at":"2019-05-20T06:28:03.000-04:00","deleted":null,"deleted_at":null,"recipe_count":30,"average_millipercent":1765,"slug":"flavorah-red-velvet","confirmed":true,"rejected":false,"vendor_url":null,"base":null,"density":1.0,"imageUrl":"","description":null,"description_raw":null,"short_description":null,"vendor_percentage":0.0,"vendor_description_raw":null,"vendor_description":null,"other_names":"","discontinued":false,"tags":{}},{"mix_id":2160010067819,"mix_sid":"rkam831n","id":8567,"name":"Root Beer","vendor":{"name":"Flavorah","abbreviation":"FLV","mix_id":2095493645177,"mix_sid":"qqnmt8qh"},"created_at":"2017-08-31T22:30:09.000-04:00","updated_at":"2019-06-19T14:44:31.000-04:00","deleted":null,"deleted_at":null,"recipe_count":206,"average_millipercent":3738,"slug":"flavorah-root-beer","confirmed":true,"rejected":false,"vendor_url":null,"base":null,"density":1.0,"imageUrl":"","description":null,"description_raw":null,"short_description":null,"vendor_percentage":0.0,"vendor_description_raw":null,"vendor_description":null,"other_names":"","discontinued":false,"tags":{}},{"mix_id":2098129106018,"mix_sid":"qrv7wbc2","id":8568,"name":"Sangria","vendor":{"name":"Flavorah","abbreviation":"FLV","mix_id":2095493645177,"mix_sid":"qqnmt8qh"},"created_at":"2017-08-31T22:30:09.000-04:00","updated_at":"2019-04-24T23:57:15.000-04:00","deleted":null,"deleted_at":null,"recipe_count":35,"average_millipercent":1848,"slug":"flavorah-sangria","confirmed":true,"rejected":false,"vendor_url":null,"base":null,"density":1.0,"imageUrl":"","description":null,"description_raw":null,"short_description":null,"vendor_percentage":0.0,"vendor_description_raw":null,"vendor_description":null,"other_names":"","discontinued":false,"tags":{}},{"mix_id":2157333063061,"mix_sid":"rj2cekyd","id":8569,"name":"Smoked Butterscotch","vendor":{"name":"Flavorah","abbreviation":"FLV","mix_id":2095493645177,"mix_sid":"qqnmt8qh"},"created_at":"2017-08-31T22:30:10.000-04:00","updated_at":"2019-06-22T21:13:30.000-04:00","deleted":null,"deleted_at":null,"recipe_count":195,"average_millipercent":883,"slug":"flavorah-smoked-butterscotch","confirmed":true,"rejected":false,"vendor_url":null,"base":null,"density":1.0,"imageUrl":"","description":null,"description_raw":null,"short_description":null,"vendor_percentage":0.0,"vendor_description_raw":null,"vendor_description":null,"other_names":"","discontinued":false,"tags":{}},{"mix_id":2139705792318,"mix_sid":"raytkzsu","id":8570,"name":"Smooth Vanilla","vendor":{"name":"Flavorah","abbreviation":"FLV","mix_id":2095493645177,"mix_sid":"qqnmt8qh"},"created_at":"2017-08-31T22:30:10.000-04:00","updated_at":"2019-06-22T16:41:31.000-04:00","deleted":null,"deleted_at":null,"recipe_count":241,"average_millipercent":313,"slug":"flavorah-smooth-vanilla","confirmed":true,"rejected":false,"vendor_url":null,"base":null,"density":1.0,"imageUrl":"","description":null,"description_raw":null,"short_description":null,"vendor_percentage":0.0,"vendor_description_raw":null,"vendor_description":null,"other_names":"","discontinued":false,"tags":{}},{"mix_id":2122393783355,"mix_sid":"r30igk6z","id":8571,"name":"Sugar Orchid","vendor":{"name":"Flavorah","abbreviation":"FLV","mix_id":2095493645177,"mix_sid":"qqnmt8qh"},"created_at":"2017-08-31T22:30:11.000-04:00","updated_at":"2019-05-07T18:11:36.000-04:00","deleted":null,"deleted_at":null,"recipe_count":29,"average_millipercent":642,"slug":"flavorah-sugar-orchid","confirmed":true,"rejected":false,"vendor_url":null,"base":null,"density":1.0,"imageUrl":"","description":null,"description_raw":null,"short_description":null,"vendor_percentage":0.0,"vendor_description_raw":null,"vendor_description":null,"other_names":"","discontinued":false,"tags":{}},{"mix_id":2125795072512,"mix_sid":"r4krhzpc","id":8572,"name":"Sun Cookie","vendor":{"name":"Flavorah","abbreviation":"FLV","mix_id":2095493645177,"mix_sid":"qqnmt8qh"},"created_at":"2017-08-31T22:30:11.000-04:00","updated_at":"2019-06-13T09:23:25.000-04:00","deleted":null,"deleted_at":null,"recipe_count":12,"average_millipercent":1000,"slug":"flavorah-sun-cookie","confirmed":true,"rejected":false,"vendor_url":null,"base":null,"density":1.0,"imageUrl":"","description":null,"description_raw":null,"short_description":null,"vendor_percentage":0.0,"vendor_description_raw":null,"vendor_description":null,"other_names":"","discontinued":false,"tags":{}},{"mix_id":2046280143341,"mix_sid":"q41qd3ot","id":8573,"name":"Vanilla Bean","vendor":{"name":"Flavorah","abbreviation":"FLV","mix_id":2095493645177,"mix_sid":"qqnmt8qh"},"created_at":"2017-08-31T22:30:11.000-04:00","updated_at":"2019-06-22T19:49:03.000-04:00","deleted":null,"deleted_at":null,"recipe_count":330,"average_millipercent":892,"slug":"flavorah-vanilla-bean","confirmed":true,"rejected":false,"vendor_url":null,"base":null,"density":1.0,"imageUrl":"","description":null,"description_raw":null,"short_description":null,"vendor_percentage":0.0,"vendor_description_raw":null,"vendor_description":null,"other_names":"","discontinued":false,"tags":{}},{"mix_id":2063683875016,"mix_sid":"qc1k3gzs","id":8574,"name":"Wheat","vendor":{"name":"Flavorah","abbreviation":"FLV","mix_id":2095493645177,"mix_sid":"qqnmt8qh"},"created_at":"2017-08-31T22:30:12.000-04:00","updated_at":"2019-06-18T07:30:05.000-04:00","deleted":null,"deleted_at":null,"recipe_count":21,"average_millipercent":489,"slug":"flavorah-wheat","confirmed":true,"rejected":false,"vendor_url":null,"base":null,"density":1.0,"imageUrl":"","description":null,"description_raw":null,"short_description":null,"vendor_percentage":0.0,"vendor_description_raw":null,"vendor_description":null,"other_names":"","discontinued":false,"tags":{}},{"mix_id":2118175099105,"mix_sid":"r12qrild","id":8575,"name":"Yam","vendor":{"name":"Flavorah","abbreviation":"FLV","mix_id":2095493645177,"mix_sid":"qqnmt8qh"},"created_at":"2017-08-31T22:30:12.000-04:00","updated_at":"2019-06-09T13:35:32.000-04:00","deleted":null,"deleted_at":null,"recipe_count":71,"average_millipercent":1150,"slug":"flavorah-yam","confirmed":true,"rejected":false,"vendor_url":null,"base":null,"density":1.0,"imageUrl":"","description":null,"description_raw":null,"short_description":null,"vendor_percentage":0.0,"vendor_description_raw":null,"vendor_description":null,"other_names":"","discontinued":false,"tags":{}},{"mix_id":2053115103817,"mix_sid":"q76rq0y1","id":8576,"name":"Pomelo","vendor":{"name":"Purilum","abbreviation":"PUR","mix_id":2105523544175,"mix_sid":"qv9icsbz"},"created_at":"2017-09-03T05:34:11.000-04:00","updated_at":"2019-01-09T23:38:57.000-05:00","deleted":null,"deleted_at":null,"recipe_count":4,"average_millipercent":3375,"slug":"purilum-pomelo","confirmed":true,"rejected":false,"vendor_url":"https://www.nicotineriver.com/collections/purilum-flavor-concentrates/products/purilum-pomelo","base":null,"density":1.0,"imageUrl":"","description":null,"description_raw":null,"short_description":null,"vendor_percentage":0.0,"vendor_description_raw":null,"vendor_description":null,"other_names":"","discontinued":false,"tags":{}},{"mix_id":2118921879009,"mix_sid":"r1f3dlnl","id":8577,"name":"Passion Fruit","vendor":{"name":"Purilum","abbreviation":"PUR","mix_id":2105523544175,"mix_sid":"qv9icsbz"},"created_at":"2017-09-03T05:34:48.000-04:00","updated_at":"2018-11-06T14:03:00.000-05:00","deleted":null,"deleted_at":null,"recipe_count":16,"average_millipercent":3250,"slug":"purilum-passion-fruit","confirmed":true,"rejected":false,"vendor_url":"https://www.nicotineriver.com/collections/purilum-flavor-concentrates/products/purilum-passion-fruit","base":null,"density":1.0,"imageUrl":"","description":null,"description_raw":null,"short_description":null,"vendor_percentage":0.0,"vendor_description_raw":null,"vendor_description":null,"other_names":"","discontinued":false,"tags":{}},{"mix_id":2049580646995,"mix_sid":"q5kbeclv","id":8578,"name":"Grapefruit Mojito","vendor":{"name":"Purilum","abbreviation":"PUR","mix_id":2105523544175,"mix_sid":"qv9icsbz"},"created_at":"2017-09-03T05:35:58.000-04:00","updated_at":"2019-01-31T15:15:03.000-05:00","deleted":null,"deleted_at":null,"recipe_count":1,"average_millipercent":6000,"slug":"purilum-grapefruit-mojito","confirmed":true,"rejected":false,"vendor_url":"https://www.nicotineriver.com/collections/purilum-flavor-concentrates/products/purilum-grapefruit-mojito","base":null,"density":1.0,"imageUrl":"","description":null,"description_raw":null,"short_description":null,"vendor_percentage":0.0,"vendor_description_raw":null,"vendor_description":null,"other_names":"","discontinued":false,"tags":{}},{"mix_id":2160114268241,"mix_sid":"rkcc9glt","id":8579,"name":"Dragon Fruit Raw","vendor":{"name":"Purilum","abbreviation":"PUR","mix_id":2105523544175,"mix_sid":"qv9icsbz"},"created_at":"2017-09-03T05:36:51.000-04:00","updated_at":"2017-09-03T08:13:52.000-04:00","deleted":null,"deleted_at":null,"recipe_count":0,"average_millipercent":0,"slug":"purilum-dragon-fruit-raw","confirmed":true,"rejected":false,"vendor_url":"https://www.nicotineriver.com/collections/purilum-flavor-concentrates/products/purilum-dragon-fruit-raw","base":null,"density":1.0,"imageUrl":"","description":null,"description_raw":null,"short_description":null,"vendor_percentage":0.0,"vendor_description_raw":null,"vendor_description":null,"other_names":"","discontinued":false,"tags":{}},{"mix_id":2046656288234,"mix_sid":"q47yb6y2","id":8580,"name":"Vanilla Nut Brittle","vendor":{"name":"Purilum","abbreviation":"PUR","mix_id":2105523544175,"mix_sid":"qv9icsbz"},"created_at":"2017-09-03T05:37:32.000-04:00","updated_at":"2019-05-21T03:31:14.000-04:00","deleted":null,"deleted_at":null,"recipe_count":22,"average_millipercent":2491,"slug":"purilum-vanilla-nut-brittle","confirmed":true,"rejected":false,"vendor_url":"https://www.nicotineriver.com/collections/purilum-flavor-concentrates/products/purilum-vanilla-nut-brittle","base":null,"density":1.0,"imageUrl":"","description":null,"description_raw":null,"short_description":null,"vendor_percentage":0.0,"vendor_description_raw":null,"vendor_description":null,"other_names":"","discontinued":false,"tags":{}},{"mix_id":2063992136164,"mix_sid":"qc6nmktg","id":8581,"name":"Acai Berry","vendor":{"name":"Purilum","abbreviation":"PUR","mix_id":2105523544175,"mix_sid":"qv9icsbz"},"created_at":"2017-09-03T05:38:21.000-04:00","updated_at":"2019-04-05T08:40:34.000-04:00","deleted":null,"deleted_at":null,"recipe_count":2,"average_millipercent":2750,"slug":"purilum-acai-berry","confirmed":true,"rejected":false,"vendor_url":"https://www.nicotineriver.com/collections/purilum-flavor-concentrates/products/purilum-acai-berry","base":null,"density":1.0,"imageUrl":"","description":null,"description_raw":null,"short_description":null,"vendor_percentage":0.0,"vendor_description_raw":null,"vendor_description":null,"other_names":"","discontinued":false,"tags":{}},{"mix_id":2126476739651,"mix_sid":"r4w1chfn","id":8582,"name":"Papaya Mango","vendor":{"name":"Purilum","abbreviation":"PUR","mix_id":2105523544175,"mix_sid":"qv9icsbz"},"created_at":"2017-09-03T05:38:59.000-04:00","updated_at":"2017-09-03T08:13:53.000-04:00","deleted":null,"deleted_at":null,"recipe_count":0,"average_millipercent":0,"slug":"purilum-papaya-mango","confirmed":true,"rejected":false,"vendor_url":"https://www.nicotineriver.com/collections/purilum-flavor-concentrates/products/purilum-papaya-mango","base":null,"density":1.0,"imageUrl":"","description":null,"description_raw":null,"short_description":null,"vendor_percentage":0.0,"vendor_description_raw":null,"vendor_description":null,"other_names":"","discontinued":false,"tags":{}},{"mix_id":2089523007160,"mix_sid":"qnww1qyg","id":8583,"name":"Kiwi","vendor":{"name":"Purilum","abbreviation":"PUR","mix_id":2105523544175,"mix_sid":"qv9icsbz"},"created_at":"2017-09-03T05:40:03.000-04:00","updated_at":"2018-11-01T21:04:00.000-04:00","deleted":null,"deleted_at":null,"recipe_count":4,"average_millipercent":2125,"slug":"purilum-kiwi","confirmed":true,"rejected":false,"vendor_url":"https://www.nicotineriver.com/collections/purilum-flavor-concentrates/products/purilum-kiwi","base":null,"density":1.0,"imageUrl":"","description":null,"description_raw":null,"short_description":null,"vendor_percentage":0.0,"vendor_description_raw":null,"vendor_description":null,"other_names":"","discontinued":false,"tags":{}},{"mix_id":2164300362971,"mix_sid":"rm9kjzyz","id":8584,"name":"Grape Soda","vendor":{"name":"Purilum","abbreviation":"PUR","mix_id":2105523544175,"mix_sid":"qv9icsbz"},"created_at":"2017-09-03T05:40:41.000-04:00","updated_at":"2019-04-13T00:57:17.000-04:00","deleted":null,"deleted_at":null,"recipe_count":4,"average_millipercent":5375,"slug":"purilum-grape-soda","confirmed":true,"rejected":false,"vendor_url":"https://www.nicotineriver.com/collections/purilum-flavor-concentrates/products/purilum-grape-soda","base":null,"density":1.0,"imageUrl":"","description":null,"description_raw":null,"short_description":null,"vendor_percentage":0.0,"vendor_description_raw":null,"vendor_description":null,"other_names":"","discontinued":false,"tags":{}},{"mix_id":2099269766336,"mix_sid":"qse30mgw","id":8585,"name":"Watermelon Cotton Candy","vendor":{"name":"Purilum","abbreviation":"PUR","mix_id":2105523544175,"mix_sid":"qv9icsbz"},"created_at":"2017-09-03T05:41:24.000-04:00","updated_at":"2019-04-20T04:51:21.000-04:00","deleted":null,"deleted_at":null,"recipe_count":12,"average_millipercent":4959,"slug":"purilum-watermelon-cotton-candy","confirmed":true,"rejected":false,"vendor_url":"https://www.nicotineriver.com/collections/purilum-flavor-concentrates/products/purilum-watermelon-cotton-candy","base":null,"density":1.0,"imageUrl":"","description":null,"description_raw":null,"short_description":null,"vendor_percentage":0.0,"vendor_description_raw":null,"vendor_description":null,"other_names":"","discontinued":false,"tags":{}}]